tests/test_Map/__init__.py
tests/test_Map/test_Map.py
tests/test_interpolate/__init__.py
tests/test_interpolate/test_interpolate_inverseDistance.py
tests/test_utils/__init__.py
tests/test_utils/test_euclidianDistance.py
tests/visual/__init__.py
tests/visual/test_visual_1d.py
topography/Map.py
topography/Noise.py
topography/Points.py
topography/__init__.py
topography/interpolate.py
topography/utils/__init__.py
topography/utils/glob.py
topography/utils/io.py
topography/utils/pile.py
topography-1.0.0.dist-info/LICENSE
topography-1.0.0.dist-info/METADATA
topography-1.0.0.dist-info/WHEEL
topography-1.0.0.dist-info/top_level.txt
topography-1.0.0.dist-info/RECORD
