Metadata-Version: 2.1
Name: topography
Version: 1.0.0
Summary: Perform interpolation on surfaces to generate topographic-style maps.
Home-page: https://github.com/XDwightsBeetsX/topography
Author: John Gutierrez
License: MIT
Keywords: topography,map,engineering,python,terrain modelling,terrain
Platform: UNKNOWN
Classifier: Programming Language :: Python :: 3
Classifier: Programming Language :: Python :: 3.8
Classifier: License :: OSI Approved :: MIT License
Requires-Python: >=3.6
Requires-Dist: numpy
Requires-Dist: matplotlib
